LICENSE.txt
MANIFEST.in
README.rst
setup.py
51degrees_mobile_detector_v3_trie_wrapper.egg-info/PKG-INFO
51degrees_mobile_detector_v3_trie_wrapper.egg-info/SOURCES.txt
51degrees_mobile_detector_v3_trie_wrapper.egg-info/dependency_links.txt
51degrees_mobile_detector_v3_trie_wrapper.egg-info/requires.txt
51degrees_mobile_detector_v3_trie_wrapper.egg-info/top_level.txt
FiftyOneDegrees/__init__.py
FiftyOneDegrees/fiftyone_degrees_mobile_detector_v3_trie_wrapper.py
data/51Degrees-LiteV3.4.trie
src/threading.c
src/threading.h
src/cityhash/LICENSE
src/cityhash/city.c
src/cityhash/city.h
src/trie/51Degrees.c
src/trie/51Degrees.h
src/trie/51Degrees.i
src/trie/51Degrees_PHP.cpp
src/trie/51Degrees_csharp.cxx
src/trie/51Degrees_go.cxx
src/trie/51Degrees_java.cpp
src/trie/51Degrees_lua.cpp
src/trie/51Degrees_node.cpp
src/trie/51Degrees_perl.cxx
src/trie/51Degrees_python.cpp
src/trie/51Degrees_python.cxx
src/trie/FiftyOneDegreesTrieV3.go
src/trie/FiftyOneDegreesTrieV3.java
src/trie/FiftyOneDegreesTrieV3.pm
src/trie/FiftyOneDegreesTrieV3.py
src/trie/FiftyOneDegreesTrieV3JNI.java
src/trie/MapStringString.java
src/trie/Match.cpp
src/trie/Match.hpp
src/trie/Match.java
src/trie/PerfTrie.c
src/trie/ProcTrie.c
src/trie/Provider.cpp
src/trie/Provider.hpp
src/trie/Provider.java
src/trie/SWIGTYPE_p_std__string.java
src/trie/SWIGTYPE_p_unsigned_char.java
src/trie/VectorString.java
src/trie/php_FiftyOneDegreesTrieV3.h