Metadata-Version: 2.1
Name: 51degrees-mobile-detector-v3-trie-wrapper
Version: 3.2.18.3
Summary: 51Degrees Mobile Detector (Lite C Trie Wrapper).
Home-page: http://51degrees.com
Author: 51Degrees.com
Author-email: info@51degrees.com
License: MPL2
Platform: UNKNOWN
Classifier: Development Status :: 5 - Production/Stable
Classifier: Intended Audience :: Developers
Classifier: Topic :: Software Development :: Libraries
Classifier: License :: OSI Approved :: Mozilla Public License 2.0 (MPL 2.0)
Classifier: Programming Language :: C
Classifier: Programming Language :: Python
Classifier: Programming Language :: Python :: 2
Classifier: Programming Language :: Python :: 2.6
Classifier: Programming Language :: Python :: 2.7
Classifier: Programming Language :: Python :: 3
Classifier: Programming Language :: Python :: 3.2
Classifier: Programming Language :: Python :: 3.3
Classifier: Operating System :: POSIX
Classifier: Operating System :: MacOS :: MacOS X
